graphql_auth/__init__.py
graphql_auth/apps.py
graphql_auth/backends.py
graphql_auth/bases.py
graphql_auth/connection.py
graphql_auth/constants.py
graphql_auth/decorators.py
graphql_auth/exceptions.py
graphql_auth/forms.py
graphql_auth/mixins.py
graphql_auth/models.py
graphql_auth/mutations.py
graphql_auth/queries.py
graphql_auth/relay.py
graphql_auth/settings.py
graphql_auth/shortcuts.py
graphql_auth/signals.py
graphql_auth/types.py
graphql_auth/utils.py
graphql_auth/migrations/0001_initial.py
graphql_auth/migrations/0002_otpcode.py
graphql_auth/migrations/__init__.py
graphql_auth/templates/email/activation_email.html
graphql_auth/templates/email/activation_subject.txt
graphql_auth/templates/email/password_reset_email.html
graphql_auth/templates/email/password_reset_subject.txt
graphql_auth/templates/email/password_set_email.html
graphql_auth/templates/email/password_set_subject.txt
django_graphene_auth_code-1.0.3.dist-info/LICENSE
django_graphene_auth_code-1.0.3.dist-info/METADATA
django_graphene_auth_code-1.0.3.dist-info/WHEEL
django_graphene_auth_code-1.0.3.dist-info/top_level.txt
django_graphene_auth_code-1.0.3.dist-info/zip-safe
django_graphene_auth_code-1.0.3.dist-info/RECORD
