Metadata-Version: 2.1
Name: django-graphene-auth-code
Version: 1.0.3
Summary: Graphql and relay authentication with Graphene for Django.
Home-page: https://github.com/kingnonso/django-graphene-auth-code
Author: Chinonso Ani
Author-email: achinonso@gmail.com
Maintainer: Chinonso Ani
License: MIT
Project-URL: Documentation, https://django-graphene-auth.readthedocs.io/en/latest/
Keywords: api graphql rest relay graphene auth jwt
Classifier: Development Status :: 4 - Beta
Classifier: Environment :: Web Environment
Classifier: Intended Audience :: Developers
Classifier: License :: OSI Approved :: MIT License
Classifier: Operating System :: OS Independent
Classifier: Programming Language :: Python
Classifier: Programming Language :: Python :: 3.10
Classifier: Programming Language :: Python :: 3.11
Classifier: Framework :: Django
Classifier: Framework :: Django :: 3.2
Classifier: Framework :: Django :: 4.2
Classifier: Framework :: Django :: 5.0
License-File: LICENSE
Requires-Dist: Django >=3.2
Requires-Dist: django-graphql-jwt ==0.4.0
Requires-Dist: django-filter >=23.5
Requires-Dist: graphene-django >=3.1.6
Requires-Dist: graphene >=3.3
Requires-Dist: PyJWT >=2.8.0
